keymate_api/__init__.py
keymate_api/sdk.py
keymate_api/sdkconfiguration.py
keymate_api/_hooks/__init__.py
keymate_api/_hooks/sdkhooks.py
keymate_api/_hooks/types.py
keymate_api/models/__init__.py
keymate_api/models/components/__init__.py
keymate_api/models/components/security.py
keymate_api/models/errors/__init__.py
keymate_api/models/errors/browse.py
keymate_api/models/errors/browsebyurl.py
keymate_api/models/errors/fast.py
keymate_api/models/errors/hybrid.py
keymate_api/models/errors/keymate.py
keymate_api/models/errors/sdkerror.py
keymate_api/models/errors/search.py
keymate_api/models/errors/searchandbrowse.py
keymate_api/models/errors/ultrafastsearch.py
keymate_api/models/operations/__init__.py
keymate_api/models/operations/browse.py
keymate_api/models/operations/browsebyurl.py
keymate_api/models/operations/document.py
keymate_api/models/operations/fast.py
keymate_api/models/operations/halloween.py
keymate_api/models/operations/help.py
keymate_api/models/operations/hybrid.py
keymate_api/models/operations/insert.py
keymate_api/models/operations/keymate.py
keymate_api/models/operations/list.py
keymate_api/models/operations/listpdfs.py
keymate_api/models/operations/metadatakb.py
keymate_api/models/operations/pdfload.py
keymate_api/models/operations/pdfpro.py
keymate_api/models/operations/pdfsearch.py
keymate_api/models/operations/pkb.py
keymate_api/models/operations/query.py
keymate_api/models/operations/queryusersknowledgebase.py
keymate_api/models/operations/resetknowledgebase.py
keymate_api/models/operations/resetusersknowledgebase.py
keymate_api/models/operations/savetopkb.py
keymate_api/models/operations/search.py
keymate_api/models/operations/searchandbrowse.py
keymate_api/models/operations/ultrafastsearch.py
keymate_api/models/operations/upsert.py
keymate_api/models/operations/upsertjson.py
keymate_api/models/operations/upserttousersknowledgebase.py
keymate_api/utils/__init__.py
keymate_api/utils/retries.py
keymate_api/utils/utils.py
Keymate_API-0.7.1.dist-info/LICENSE.md
Keymate_API-0.7.1.dist-info/METADATA
Keymate_API-0.7.1.dist-info/WHEEL
Keymate_API-0.7.1.dist-info/top_level.txt
Keymate_API-0.7.1.dist-info/RECORD
